ptconvert/__init__.py
ptconvert/_version.py
ptconvert/ptconvert.py
ptconvert/modules/_baseclass.py
ptconvert/modules/burp_report.py
ptconvert/modules/swagger.py
ptconvert/modules/tree_command.py
ptconvert/modules/url_wordlist.py
ptconvert/modules/__pycache__/_baseclass.cpython-311.pyc
ptconvert/modules/__pycache__/_baseclass.cpython-312.pyc
ptconvert/modules/__pycache__/_baseclass.cpython-313.pyc
ptconvert/modules/__pycache__/burp_report.cpython-311.pyc
ptconvert/modules/__pycache__/burp_report.cpython-312.pyc
ptconvert/modules/__pycache__/csv.cpython-311.pyc
ptconvert/modules/__pycache__/open_api.cpython-312.pyc
ptconvert/modules/__pycache__/swagger.cpython-311.pyc
ptconvert/modules/__pycache__/swagger.cpython-312.pyc
ptconvert/modules/__pycache__/tree_command.cpython-313.pyc
ptconvert/modules/__pycache__/url_wordlist.cpython-311.pyc
ptconvert-0.0.4.dist-info/licenses/LICENSE
ptconvert-0.0.4.dist-info/METADATA
ptconvert-0.0.4.dist-info/WHEEL
ptconvert-0.0.4.dist-info/entry_points.txt
ptconvert-0.0.4.dist-info/top_level.txt
ptconvert-0.0.4.dist-info/RECORD
